newrelic_airflow_plugin/__init__.py
newrelic_airflow_plugin/newrelic_plugin.py
newrelic_airflow_plugin/version.py
newrelic_airflow_plugin-0.2.0.dist-info/LICENSE
newrelic_airflow_plugin-0.2.0.dist-info/METADATA
newrelic_airflow_plugin-0.2.0.dist-info/THIRD_PARTY_NOTICES.rst
newrelic_airflow_plugin-0.2.0.dist-info/WHEEL
newrelic_airflow_plugin-0.2.0.dist-info/entry_points.txt
newrelic_airflow_plugin-0.2.0.dist-info/top_level.txt
newrelic_airflow_plugin-0.2.0.dist-info/RECORD
